img_pipe/.DS_Store
img_pipe/.xdebug_mris_curvature_stats
img_pipe/To do requests
img_pipe/__init__.py
img_pipe/__init__.pyc
img_pipe/dependencies.sh
img_pipe/img_pipe.py
img_pipe/img_pipe.pyc
img_pipe/pyscript.m
img_pipe/SupplementalFiles/FS_colorLUT.py
img_pipe/SupplementalFiles/FS_colorLUT.pyc
img_pipe/SupplementalFiles/FreeSurferLUTRGBValues.npy
img_pipe/SupplementalFiles/FreeSurferLookupTable
img_pipe/SupplementalFiles/__init__.py
img_pipe/SupplementalFiles/__init__.pyc
img_pipe/SupplementalFiles/clingrid_inds.mat
img_pipe/SupplementalFiles/cvs_avg35_inMNI152_affine_subj.txt
img_pipe/SupplementalFiles/img_pipe_results.png
img_pipe/SupplementalFiles/workflow.png
img_pipe/SupplementalFiles/__pycache__/FS_colorLUT.cpython-35.pyc
img_pipe/SupplementalFiles/__pycache__/__init__.cpython-35.pyc
img_pipe/SupplementalScripts/.DS_Store
img_pipe/SupplementalScripts/__init__.py
img_pipe/SupplementalScripts/__init__.pyc
img_pipe/SupplementalScripts/acpc.py
img_pipe/SupplementalScripts/acpc_picker.py
img_pipe/SupplementalScripts/aseg2srf.sh
img_pipe/SupplementalScripts/electrode_picker.py
img_pipe/SupplementalScripts/spyder_crash.log
img_pipe/SupplementalScripts/__pycache__/electrode_picker.cpython-35.pyc
img_pipe/SupplementalScripts/icons/.DS_Store
img_pipe/SupplementalScripts/icons/leftbrain.png
img_pipe/SupplementalScripts/icons/leftbrain_blackbg.png
img_pipe/SupplementalScripts/icons/rightbrain_blackbg.png
img_pipe/__pycache__/__init__.cpython-35.pyc
img_pipe/__pycache__/__init__.cpython-36.pyc
img_pipe/__pycache__/img_pipe.cpython-35.pyc
img_pipe/__pycache__/img_pipe.cpython-36.pyc
img_pipe/plotting/__init__.py
img_pipe/plotting/__init__.pyc
img_pipe/plotting/ctmr_brain_plot.py
img_pipe/plotting/ctmr_brain_plot.pyc
img_pipe/plotting/ctmr_brain_plot_example.ipynb
img_pipe/plotting/ctmr_brain_plot_simple_example.ipynb
img_pipe/plotting/loc_colormap.mat
img_pipe/plotting/mlab_3D_to_2D.py
img_pipe/plotting/mlab_3D_to_2D.pyc
img_pipe-2017.9.26.1.dist-info/DESCRIPTION.rst
img_pipe-2017.9.26.1.dist-info/METADATA
img_pipe-2017.9.26.1.dist-info/RECORD
img_pipe-2017.9.26.1.dist-info/WHEEL
img_pipe-2017.9.26.1.dist-info/dependency_links.txt
img_pipe-2017.9.26.1.dist-info/metadata.json
img_pipe-2017.9.26.1.dist-info/top_level.txt
