Metadata-Version: 1.1
Name: img-pipe
Version: 2017.9.26.1
Summary: Image processing pipeline for localization and identification of electrodes for electrocorticography
Home-page: https://github.com/ChangLabUcsf/img_pipe
Author: Liberty Hamilton
Author-email: libertyhamilton@gmail.com
License: UNKNOWN
Platform: UNKNOWN
Classifier: Intended Audience :: Science/Research
Classifier: Intended Audience :: Education
Classifier: Programming Language :: Python :: 2.7
Classifier: Topic :: Scientific/Engineering
Classifier: Topic :: Scientific/Engineering :: Visualization
Classifier: Topic :: Scientific/Engineering :: Medical Science Apps.
